{"note":"This file is an internal implementation detail to speed up HTML report generation. Its format can change at any time. You might be looking for the JSON report: https://coverage.rtfd.io/cmd.html#cmd-json","format":5,"version":"7.13.5","globals":"ddb9896d0d17f60deae90b74f20cdb1b","files":{"z_509fd8af0f7a1b49_admin_py":{"hash":"1d5e9fdc15b08fecaa3606abea9f5b75","index":{"url":"z_509fd8af0f7a1b49_admin_py.html","file":"accounts/admin.py","description":"","nums":{"precision":0,"n_files":1,"n_statements":1,"n_excluded":0,"n_missing":0,"n_branches":0,"n_partial_branches":0,"n_missing_branches":0}}},"z_509fd8af0f7a1b49_apps_py":{"hash":"f0a641c2aba00796b7692f988d081497","index":{"url":"z_509fd8af0f7a1b49_apps_py.html","file":"accounts/apps.py","description":"","nums":{"precision":0,"n_files":1,"n_statements":4,"n_excluded":0,"n_missing":0,"n_branches":0,"n_partial_branches":0,"n_missing_branches":0}}},"z_509fd8af0f7a1b49_forms_py":{"hash":"0caa4afb5ad10fb7c2378b1cb6cc8e59","index":{"url":"z_509fd8af0f7a1b49_forms_py.html","file":"accounts/forms.py","description":"","nums":{"precision":0,"n_files":1,"n_statements":12,"n_excluded":0,"n_missing":0,"n_branches":0,"n_partial_branches":0,"n_missing_branches":0}}},"z_509fd8af0f7a1b49_serializers_py":{"hash":"ed76ef8ede8a3e329b54ece2ba5e7575","index":{"url":"z_509fd8af0f7a1b49_serializers_py.html","file":"accounts/serializers.py","description":"","nums":{"precision":0,"n_files":1,"n_statements":6,"n_excluded":0,"n_missing":6,"n_branches":0,"n_partial_branches":0,"n_missing_branches":0}}},"z_509fd8af0f7a1b49_urls_py":{"hash":"d8661b0071d3c51e92ad651c64e2b80d","index":{"url":"z_509fd8af0f7a1b49_urls_py.html","file":"accounts/urls.py","description":"","nums":{"precision":0,"n_files":1,"n_statements":7,"n_excluded":0,"n_missing":7,"n_branches":0,"n_partial_branches":0,"n_missing_branches":0}}},"z_509fd8af0f7a1b49_views_py":{"hash":"a7f403339ca9b6764063ced8b5f91547","index":{"url":"z_509fd8af0f7a1b49_views_py.html","file":"accounts/views.py","description":"","nums":{"precision":0,"n_files":1,"n_statements":49,"n_excluded":0,"n_missing":49,"n_branches":0,"n_partial_branches":0,"n_missing_branches":0}}},"z_1ea838694151cac8_asgi_py":{"hash":"e6431d7a1a75ee1b5fe03190f5760369","index":{"url":"z_1ea838694151cac8_asgi_py.html","file":"config/asgi.py","description":"","nums":{"precision":0,"n_files":1,"n_statements":4,"n_excluded":0,"n_missing":4,"n_branches":0,"n_partial_branches":0,"n_missing_branches":0}}},"z_1ea838694151cac8_settings_py":{"hash":"9554fe35cde92fe2fe0422c1909ebeed","index":{"url":"z_1ea838694151cac8_settings_py.html","file":"config/settings.py","description":"","nums":{"precision":0,"n_files":1,"n_statements":31,"n_excluded":0,"n_missing":3,"n_branches":0,"n_partial_branches":0,"n_missing_branches":0}}},"z_1ea838694151cac8_urls_py":{"hash":"2bd6e5704d1fb1fa39f2e17129c430f3","index":{"url":"z_1ea838694151cac8_urls_py.html","file":"config/urls.py","description":"","nums":{"precision":0,"n_files":1,"n_statements":3,"n_excluded":0,"n_missing":3,"n_branches":0,"n_partial_branches":0,"n_missing_branches":0}}},"z_1ea838694151cac8_wsgi_py":{"hash":"c096a4f4d5aacca7f278e5e824425825","index":{"url":"z_1ea838694151cac8_wsgi_py.html","file":"config/wsgi.py","description":"","nums":{"precision":0,"n_files":1,"n_statements":4,"n_excluded":0,"n_missing":4,"n_branches":0,"n_partial_branches":0,"n_missing_branches":0}}},"manage_py":{"hash":"86ae7d090591307404ed49ffce8ddc2d","index":{"url":"manage_py.html","file":"manage.py","description":"","nums":{"precision":0,"n_files":1,"n_statements":8,"n_excluded":0,"n_missing":8,"n_branches":0,"n_partial_branches":0,"n_missing_branches":0}}}}}